Metadata-Version: 1.0
Name: templot
Version: 1.1
Summary: Python package for visualizing time evolution.
Home-page: https://github.com/khllkcm/templot
Author: Khalil Kacem
Author-email: khail@kacem.xyz
License: UNKNOWN
Platform: UNKNOWN
